azure/mgmt/informaticadatamanagement/__init__.py
azure/mgmt/informaticadatamanagement/_configuration.py
azure/mgmt/informaticadatamanagement/_informatica_data_mgmt_client.py
azure/mgmt/informaticadatamanagement/_patch.py
azure/mgmt/informaticadatamanagement/_serialization.py
azure/mgmt/informaticadatamanagement/_version.py
azure/mgmt/informaticadatamanagement/py.typed
azure/mgmt/informaticadatamanagement/aio/__init__.py
azure/mgmt/informaticadatamanagement/aio/_configuration.py
azure/mgmt/informaticadatamanagement/aio/_informatica_data_mgmt_client.py
azure/mgmt/informaticadatamanagement/aio/_patch.py
azure/mgmt/informaticadatamanagement/aio/operations/__init__.py
azure/mgmt/informaticadatamanagement/aio/operations/_operations.py
azure/mgmt/informaticadatamanagement/aio/operations/_organizations_operations.py
azure/mgmt/informaticadatamanagement/aio/operations/_patch.py
azure/mgmt/informaticadatamanagement/aio/operations/_serverless_runtimes_operations.py
azure/mgmt/informaticadatamanagement/models/__init__.py
azure/mgmt/informaticadatamanagement/models/_informatica_data_mgmt_client_enums.py
azure/mgmt/informaticadatamanagement/models/_models_py3.py
azure/mgmt/informaticadatamanagement/models/_patch.py
azure/mgmt/informaticadatamanagement/operations/__init__.py
azure/mgmt/informaticadatamanagement/operations/_operations.py
azure/mgmt/informaticadatamanagement/operations/_organizations_operations.py
azure/mgmt/informaticadatamanagement/operations/_patch.py
azure/mgmt/informaticadatamanagement/operations/_serverless_runtimes_operations.py
azure_mgmt_informaticadatamanagement-1.0.0.dist-info/LICENSE
azure_mgmt_informaticadatamanagement-1.0.0.dist-info/METADATA
azure_mgmt_informaticadatamanagement-1.0.0.dist-info/WHEEL
azure_mgmt_informaticadatamanagement-1.0.0.dist-info/top_level.txt
azure_mgmt_informaticadatamanagement-1.0.0.dist-info/RECORD
